{
  "$schema": "https://raw.githubusercontent.com/earendil-works/pi/main/packages/coding-agent/src/modes/interactive/theme/theme-schema.json",
  "name": "omarchy-system",
  "vars": {
    "background": "#080706",
    "foreground": "#d0c3b4",
    "accent": "#7a8796",
    "selectionBackground": "#5a6674",
    "selectionForeground": "#080706",
    "selectedBackground": "#212326",
    "color0": "#080706",
    "color1": "#96423c",
    "color2": "#51604f",
    "color3": "#a67a43",
    "color4": "#5a6674",
    "color5": "#7b5a6a",
    "color6": "#8c6f4b",
    "color7": "#d0c3b4",
    "color8": "#6f665f",
    "color9": "#a5342f",
    "color10": "#667863",
    "color11": "#c08b4a",
    "color12": "#7a8796",
    "color13": "#967284",
    "color14": "#c4ab84",
    "color15": "#f7f1ea",
    "panel": "#141210",
    "panelAlt": "#1c1a17",
    "panelPending": "#161617",
    "panelSuccess": "#11120f",
    "panelError": "#190e0c",
    "border": "#443f3a",
    "borderMuted": "#302d29",
    "mutedText": "#8c8379",
    "dimText": "#68615a"
  },
  "colors": {
    "accent": "accent",
    "border": "border",
    "borderAccent": "accent",
    "borderMuted": "borderMuted",
    "success": "color2",
    "error": "color1",
    "warning": "color3",
    "muted": "mutedText",
    "dim": "dimText",
    "text": "foreground",
    "thinkingText": "dimText",
    "selectedBg": "selectedBackground",
    "userMessageBg": "panel",
    "userMessageText": "foreground",
    "customMessageBg": "panel",
    "customMessageText": "foreground",
    "customMessageLabel": "accent",
    "toolPendingBg": "panelPending",
    "toolSuccessBg": "panelSuccess",
    "toolErrorBg": "panelError",
    "toolTitle": "accent",
    "toolOutput": "foreground",
    "mdHeading": "color5",
    "mdLink": "accent",
    "mdLinkUrl": "color6",
    "mdCode": "color6",
    "mdCodeBlock": "foreground",
    "mdCodeBlockBorder": "borderMuted",
    "mdQuote": "mutedText",
    "mdQuoteBorder": "borderMuted",
    "mdHr": "borderMuted",
    "mdListBullet": "color5",
    "toolDiffAdded": "color2",
    "toolDiffRemoved": "color1",
    "toolDiffContext": "mutedText",
    "syntaxComment": "dimText",
    "syntaxKeyword": "color5",
    "syntaxFunction": "color4",
    "syntaxVariable": "accent",
    "syntaxString": "color2",
    "syntaxNumber": "color3",
    "syntaxType": "color4",
    "syntaxOperator": "color5",
    "syntaxPunctuation": "mutedText",
    "thinkingOff": "borderMuted",
    "thinkingMinimal": "accent",
    "thinkingLow": "color4",
    "thinkingMedium": "color5",
    "thinkingHigh": "color3",
    "thinkingXhigh": "color1",
    "bashMode": "color3"
  },
  "export": {
    "pageBg": "#080706",
    "cardBg": "#141210",
    "infoBg": "#1c1a17"
  }
}
